<BFTypedBinder binderType="BirdElephant_Adult_M">
   <types>
      <entity>
         <actor>
            <animal>
               <Aves>
                  <Struthioniformes>
                     <Aepyornithidae>
                        <BirdElephant>
                           <BirdElephant_Adult>
                              <BirdElephant_Adult_M/>
                           </BirdElephant_Adult>
                        </BirdElephant>
                     </Aepyornithidae>
                  </Struthioniformes>
               </Aves>
            </animal>
         </actor>
      </entity>
   </types>
   <instance>
      <BFGEntity/>
   </instance>
   <shared>
      <UIToggleButton template="adopt">
         <UIAspect>
            <default image="entities/units/animals/BirdElephant/BirdElephant_Adult_F_icon.dds"/>
         </UIAspect>
         <on>
            <event msg="ZT_SETPLACEMENTOBJECT" data="BFString" string="BirdElephant_Adult_M"/>
         </on>
      </UIToggleButton>
      <BFAIEntityDataShared b_Male="1" f_adoptCount="rand(1,1)"/>
   </shared>
   <binder>
      <BFNamedBinder binderName="mainObj">
         <instance>
            <BFPhysObj>
               <BFActorComponent actorfile="entities/units/animals/BirdElephant/BirdElephant_Adult_F.bfm" scale="0.9"/>
            </BFPhysObj>
         </instance>
      </BFNamedBinder>
   </binder>
</BFTypedBinder>
